{
    "actions": [],
    "allow_rename": 0,
    "creation": "2025-04-23 12:41:29",
    "doctype": "DocType",
    "editable_grid": 1,
    "engine": "InnoDB",
    "field_order": [
      "status_pajak",
      "ptkp_amount",
      "description"
    ],
    "fields": [
      {
        "fieldname": "status_pajak",
        "fieldtype": "Select",
        "in_list_view": 1,
        "label": "Status Pajak",
        "options": "TK0\nTK1\nTK2\nTK3\nK0\nK1\nK2\nK3\nHB0\nHB1\nHB2\nHB3",
        "reqd": 1
      },
      {
        "fieldname": "ptkp_amount",
        "fieldtype": "Currency",
        "in_list_view": 1,
        "label": "PTKP Amount",
        "reqd": 1
      },
      {
        "fieldname": "description",
        "fieldtype": "Small Text",
        "label": "Description"
      }
    ],
    "istable": 1,
    "links": [],
    "modified": "2025-04-23 12:41:29",
    "modified_by": "Administrator",
    "module": "Payroll Indonesia",
    "name": "PPh 21 PTKP",
    "owner": "Administrator",
    "permissions": [],
    "sort_field": "modified",
    "sort_order": "DESC"
  }